MetaDefender/__init__.py
MetaDefender/api.py
MetaDefender_api-1.0.7.dist-info/LICENSE
MetaDefender_api-1.0.7.dist-info/METADATA
MetaDefender_api-1.0.7.dist-info/WHEEL
MetaDefender_api-1.0.7.dist-info/top_level.txt
MetaDefender_api-1.0.7.dist-info/RECORD
