Metadata-Version: 2.1
Name: MetaDefender_api
Version: 1.0.7
Summary: A simple MetaDefender Api wrapper
Home-page: https://github.com/cookie0o
Author: cookie0_o
Author-email: raphael.contact@zohomail.eu
Classifier: Programming Language :: Python :: 3
Classifier: License :: OSI Approved :: MIT License
Classifier: Operating System :: OS Independent
Requires-Python: >=3.7
License-File: LICENSE
